doctorcheck/__init__.py
doctorcheck/apps.py
doctorcheck/health_logic.py
doctorcheck/urls.py
doctorcheck/views.py
doctorcheck/static/doctorcheck/css/style.css
doctorcheck/static/doctorcheck/js/script.js
doctorcheck/templates/doctorcheck/base.html
doctorcheck/templates/doctorcheck/health_check.html
doctorcheck-0.13.0.dist-info/METADATA
doctorcheck-0.13.0.dist-info/WHEEL
doctorcheck-0.13.0.dist-info/top_level.txt
doctorcheck-0.13.0.dist-info/RECORD
