Metadata-Version: 2.4
Name: doctorcheck
Version: 0.13.0
Summary: A reusable Django app for health check logic.
Author: Keita
Author-email: keitamohamed1432@email.com
License: MIT
Classifier: Framework :: Django
Classifier: Framework :: Django :: 3.2
Classifier: Programming Language :: Python :: 3
Classifier: Programming Language :: Python :: 3.10
Classifier: License :: OSI Approved :: MIT License
Classifier: Operating System :: OS Independent
Requires-Python: >=3.6
Requires-Dist: django>=3.2
Dynamic: author
Dynamic: author-email
Dynamic: classifier
Dynamic: description
Dynamic: description-content-type
Dynamic: license
Dynamic: requires-dist
Dynamic: requires-python
Dynamic: summary
